reweave/__init__.py
reweave/ai/__init__.py
reweave/ai/openai_service.py
reweave/utils/__init__.py
reweave/utils/env_utils.py
reweave/utils/fs_utils.py
reweave/workflows/__init__.py
reweave/workflows/final_storytelling_workflows/__init__.py
reweave/workflows/final_storytelling_workflows/base_workflow.py
reweave/workflows/final_storytelling_workflows/graphical_story_workflow/__init__.py
reweave/workflows/final_storytelling_workflows/graphical_story_workflow/commons.py
reweave/workflows/final_storytelling_workflows/graphical_story_workflow/footage_builder.py
reweave/workflows/final_storytelling_workflows/graphical_story_workflow/graphical_story_repo.py
reweave/workflows/final_storytelling_workflows/graphical_story_workflow/graphical_story_workflow.py
reweave/workflows/final_storytelling_workflows/graphical_story_workflow/story_builder.py
reweave/workflows/independent_graphic_library_workflows/__init__.py
reweave/workflows/independent_graphic_library_workflows/base_workflow.py
reweave/workflows/independent_graphic_library_workflows/graphical_story_openai_workflow.py
reweave-0.1.1.dist-info/LICENSE
reweave-0.1.1.dist-info/METADATA
reweave-0.1.1.dist-info/WHEEL
reweave-0.1.1.dist-info/top_level.txt
reweave-0.1.1.dist-info/RECORD
