Metadata-Version: 2.1
Name: reweave
Version: 0.1.1
Summary: Reave is a AI automated video creator
Author: Chandresh
Author-email: chandresh.code@gmail.com
License-File: LICENSE
Requires-Dist: numpy
Requires-Dist: requests
Requires-Dist: openai
Requires-Dist: moviepy
Requires-Dist: pydantic
